rcom/__init__.py
rcom/rcom_client.py
rcom/rcom_registry.py
rcom/rcom_server.py
rcom-0.1.11.dist-info/licenses/LICENSE
rcom-0.1.11.dist-info/METADATA
rcom-0.1.11.dist-info/WHEEL
rcom-0.1.11.dist-info/top_level.txt
rcom-0.1.11.dist-info/RECORD
